{
  "outDir": "./main_apps/main-react/src/services",
  "templatePath": "./pontTemplate",
  "usingMultipleOrigins": true,
  "mocks": {
    "enable": true,
    "wrapper": "{\"code\": 20000, \"success\": true, \"data\": {response}, \"message\": \"\"}",
    "containDataSources": []
  },
  "origins": [
    {
      "name": "authorization",
      "originUrl": "http://platform-center.jxzk.thundersdata.com:38204/auth/v2/api-docs"
    },
    {
      "name": "platform",
      "originUrl": "http://192.168.1.235:8090/v2/api-docs"
    }
  ]
}
